luna_soc/__init__.py
luna_soc/top_level_cli.py
luna_soc/gateware/__init__.py
luna_soc/gateware/core/__init__.py
luna_soc/gateware/core/blockram.py
luna_soc/gateware/core/ila.py
luna_soc/gateware/core/timer.py
luna_soc/gateware/core/uart.py
luna_soc/gateware/core/spiflash/__init__.py
luna_soc/gateware/core/spiflash/controller.py
luna_soc/gateware/core/spiflash/mmap.py
luna_soc/gateware/core/spiflash/phy.py
luna_soc/gateware/core/spiflash/port.py
luna_soc/gateware/core/spiflash/utils.py
luna_soc/gateware/core/usb2/__init__.py
luna_soc/gateware/core/usb2/device.py
luna_soc/gateware/core/usb2/ep_control.py
luna_soc/gateware/core/usb2/ep_in.py
luna_soc/gateware/core/usb2/ep_out.py
luna_soc/gateware/core/usb2/ulpi.py
luna_soc/gateware/cpu/__init__.py
luna_soc/gateware/cpu/ic.py
luna_soc/gateware/cpu/minerva.py
luna_soc/gateware/cpu/vexriscv.py
luna_soc/gateware/cpu/verilog/vexriscv/vexriscv_cynthion+jtag.v
luna_soc/gateware/cpu/verilog/vexriscv/vexriscv_cynthion.v
luna_soc/gateware/cpu/verilog/vexriscv/vexriscv_imac+dcache.v
luna_soc/gateware/cpu/verilog/vexriscv/vexriscv_imac+litex.v
luna_soc/gateware/cpu/verilog/vexriscv/vexriscv_imc.v
luna_soc/gateware/provider/cynthion.py
luna_soc/gateware/vendor/__init__.py
luna_soc/gateware/vendor/amaranth_soc/__init__.py
luna_soc/gateware/vendor/amaranth_soc/event.py
luna_soc/gateware/vendor/amaranth_soc/gpio.py
luna_soc/gateware/vendor/amaranth_soc/memory.py
luna_soc/gateware/vendor/amaranth_soc/periph.py
luna_soc/gateware/vendor/amaranth_soc/csr/__init__.py
luna_soc/gateware/vendor/amaranth_soc/csr/action.py
luna_soc/gateware/vendor/amaranth_soc/csr/bus.py
luna_soc/gateware/vendor/amaranth_soc/csr/event.py
luna_soc/gateware/vendor/amaranth_soc/csr/reg.py
luna_soc/gateware/vendor/amaranth_soc/csr/wishbone.py
luna_soc/gateware/vendor/amaranth_soc/wishbone/__init__.py
luna_soc/gateware/vendor/amaranth_soc/wishbone/bus.py
luna_soc/gateware/vendor/amaranth_soc/wishbone/sram.py
luna_soc/gateware/vendor/amaranth_stdio/__init__.py
luna_soc-0.3.2.dist-info/licenses/LICENSE.txt
luna_soc-0.3.2.dist-info/METADATA
luna_soc-0.3.2.dist-info/WHEEL
luna_soc-0.3.2.dist-info/top_level.txt
luna_soc-0.3.2.dist-info/RECORD
