Metadata-Version: 2.4
Name: luna-soc
Version: 0.3.2
Summary: Amaranth HDL libary for building SoCs with LUNA USB peripherals.
Author-email: Great Scott Gadgets <dev@greatscottgadgets.com>
License: BSD
Project-URL: Documentation, https://luna-soc.readthedocs.io
Project-URL: Repository, https://github.com/greatscottgadgets/luna-soc
Project-URL: Issues, https://github.com/greatscottgadgets/luna-soc/issues
Classifier: Development Status :: 4 - Beta
Classifier: Programming Language :: Python :: 3
Classifier: License :: OSI Approved :: BSD License
Classifier: Operating System :: OS Independent
Classifier: Natural Language :: English
Classifier: Environment :: Console
Classifier: Environment :: Other Environment
Classifier: Intended Audience :: Developers
Classifier: Intended Audience :: Science/Research
Classifier: Topic :: Scientific/Engineering :: Electronic Design Automation (EDA)
Classifier: Topic :: System :: Hardware :: Universal Serial Bus (USB)
Requires-Python: >=3.9
License-File: LICENSE.txt
Requires-Dist: luna-usb~=0.2
Dynamic: license-file
